LICENSE
disrepair/__init__.py
disrepair/__main__.py
disrepair/check.py
disrepair/cmd.py
disrepair/options.py
disrepair/reqfile.py
disrepair-1.0.0.dist-info/LICENSE
disrepair-1.0.0.dist-info/METADATA
disrepair-1.0.0.dist-info/WHEEL
disrepair-1.0.0.dist-info/entry_points.txt
disrepair-1.0.0.dist-info/RECORD
