Metadata-Version: 2.1
Name: disrepair
Version: 1.0.0
Summary: Check and update out-of-date Python packages in requirements files
Home-page: https://github.com/divad/disrepair
License: GPL3
Author: David Bell
Author-email: dave@evad.io
Requires-Python: >=3.8,<4.0
Classifier: Environment :: Console
Classifier: License :: Other/Proprietary License
Classifier: Operating System :: OS Independent
Classifier: Programming Language :: Python :: 3
Classifier: Programming Language :: Python :: 3.8
Classifier: Programming Language :: Python :: 3.9
Classifier: Programming Language :: Python :: 3.10
Classifier: Programming Language :: Python :: 3.11
Classifier: Programming Language :: Python :: 3.12
Classifier: Topic :: Software Development :: Libraries :: Python Modules
Classifier: Topic :: Utilities
Requires-Dist: click (>=8.0)
Requires-Dist: packaging (>=21.0)
Requires-Dist: pypi-simple (>=1.5.0)
Requires-Dist: requests (>=2.0)
Requires-Dist: requirements-parser (>=0.9.0)
Requires-Dist: rich (>=12.0)
Requires-Dist: setuptools (>=60)
Project-URL: Repository, https://github.com/divad/disrepair
